[
  {
    "title": "Book Review - Choose Yourself By James Altucher",
    "url": "https://www.youtube.com/watch?v=Mgzdcm5uT80",
    "beforeImage": "images/before/video1_before.jpg",
    "afterImage": "images/after/video1_after.jpeg"
  },
  {
    "title": "Wean in 15 - Up to date Advice and 100 Quick Recipes From Joe Wicks",
    "url": "https://www.youtube.com/watch?v=vjs4TXlO5JU",
    "beforeImage": "images/before/video2_before.JPG",
    "afterImage": "images/after/video2_after.jpeg"
  },
  {
    "title": "Deep Work: Rules for Focused Success in a Distracted World by Cal Newport",
    "url": "https://www.youtube.com/watch?v=QgEw8XSfA2U",
    "beforeImage": "images/before/video3_before.JPG",
    "afterImage": "images/after/video3_after.jpeg"
  },
  {
    "title": "The Magic of Manifesting: 15 Advanced Techniques To Attract Your Best Life - Ryuu Shinohara",
    "url": "https://www.youtube.com/watch?v=wzMb_GBRRig",
    "beforeImage": "images/before/video4_before.JPG",
    "afterImage": "images/after/video4_after.jpeg"
  },
  {
    "title": "All The Lonely People by Mike Gayle",
    "url": "https://www.youtube.com/watch?v=NKOeqTPgLw8",
    "beforeImage": "images/before/video5_before.JPG",
    "afterImage": "images/after/video5_after.jpeg"
  },
  {
    "title": "She Thinks Like a Boss : 9 Essential Skills for New Female Leaders By Jemma Roedel",
    "url": "https://www.youtube.com/watch?v=7w1zJcFT2dA",
    "beforeImage": "images/before/video6_before.JPG",
    "afterImage": "images/after/video6_after.jpeg"
  }
]
